sdlc_genai_databricks/__init__.py
sdlc_genai_databricks/core.py
sdlc_genai_databricks-0.1.7.dist-info/licenses/LICENSE
sdlc_genai_databricks-0.1.7.dist-info/METADATA
sdlc_genai_databricks-0.1.7.dist-info/WHEEL
sdlc_genai_databricks-0.1.7.dist-info/top_level.txt
sdlc_genai_databricks-0.1.7.dist-info/RECORD
