Metadata-Version: 2.4
Name: sdlc-genai-databricks
Version: 0.1.7
Summary: A Python package that integrates GenAI, GitHub, and Databricks for SDLC automation.
Author-email: Your Name <you@example.com>
License: MIT
Project-URL: Homepage, https://github.com/yourusername/sdlc-genai-databricks
Project-URL: Repository, https://github.com/yourusername/sdlc-genai-databricks
Project-URL: Issues, https://github.com/yourusername/sdlc-genai-databricks/issues
Keywords: sdlc,genai,databricks,pyspark,github
Requires-Python: >=3.8
License-File: LICENSE
Requires-Dist: requests
Requires-Dist: pandas
Requires-Dist: PyMuPDF
Dynamic: license-file
